renats/__init__.py
renats/client/__init__.py
renats/client/client.py
renats/client/types.py
renats/connection/__init__.py
renats/connection/base.py
renats/connection/connection.py
renats/connection/tcp.py
renats/protocol/__init__.py
renats/protocol/exceptions.py
renats/protocol/messages/__init__.py
renats/protocol/messages/base.py
renats/protocol/messages/msg.py
renats/protocol/messages/pub.py
renats/protocol/messages/service.py
renats/protocol/messages/sub.py
renats/protocol/protocol.py
renats/protocol/utils.py
renats-0.2.0.dist-info/METADATA
renats-0.2.0.dist-info/WHEEL
renats-0.2.0.dist-info/RECORD
