Metadata-Version: 2.1
Name: renats
Version: 0.2.0
Summary: 
Author: Respirens
Author-email: thesergiyprotsanin@gmail.com
Requires-Python: >=3.10,<4.0
Classifier: Programming Language :: Python :: 3
Classifier: Programming Language :: Python :: 3.10
Classifier: Programming Language :: Python :: 3.11
Requires-Dist: msgspec (>=0.15.1,<0.16.0)
Requires-Dist: typing-extensions (>=4.6.3,<5.0.0)
